odoo9_addon_account_tax_balance-9.0.1.2.2-py3.6-nspkg.pth
odoo_addons/account_tax_balance/README.rst
odoo_addons/account_tax_balance/__init__.py
odoo_addons/account_tax_balance/__openerp__.py
odoo_addons/account_tax_balance/hooks.py
odoo_addons/account_tax_balance/i18n/account_tax_balance.pot
odoo_addons/account_tax_balance/i18n/ca.po
odoo_addons/account_tax_balance/i18n/de.po
odoo_addons/account_tax_balance/i18n/es.po
odoo_addons/account_tax_balance/i18n/fr.po
odoo_addons/account_tax_balance/i18n/pt.po
odoo_addons/account_tax_balance/models/__init__.py
odoo_addons/account_tax_balance/models/account_move.py
odoo_addons/account_tax_balance/models/account_tax.py
odoo_addons/account_tax_balance/static/description/icon.png
odoo_addons/account_tax_balance/static/description/tax_balance.png
odoo_addons/account_tax_balance/tests/__init__.py
odoo_addons/account_tax_balance/tests/test_account_tax_balance.py
odoo_addons/account_tax_balance/views/account_move_view.xml
odoo_addons/account_tax_balance/views/account_tax_view.xml
odoo_addons/account_tax_balance/wizard/__init__.py
odoo_addons/account_tax_balance/wizard/open_tax_balances.py
odoo_addons/account_tax_balance/wizard/open_tax_balances_view.xml
odoo9_addon_account_tax_balance-9.0.1.2.2.dist-info/METADATA
odoo9_addon_account_tax_balance-9.0.1.2.2.dist-info/WHEEL
odoo9_addon_account_tax_balance-9.0.1.2.2.dist-info/namespace_packages.txt
odoo9_addon_account_tax_balance-9.0.1.2.2.dist-info/top_level.txt
odoo9_addon_account_tax_balance-9.0.1.2.2.dist-info/RECORD
