Metadata-Version: 2.1
Name: odoo9-addon-account-tax-balance
Version: 9.0.1.2.2
Summary: Compute tax balances based on date range
Home-page: https://www.agilebg.com/
Author: Agile Business Group, Therp BV, Tecnativa, ACSONE SA/NV, Odoo Community Association (OCA)
Author-email: support@odoo-community.org
License: AGPL-3
Platform: UNKNOWN
Classifier: Programming Language :: Python
Classifier: Framework :: Odoo
Classifier: License :: OSI Approved :: GNU Affero General Public License v3
Requires-Python: ~=2.7
Requires-Dist: odoo9-addon-date-range
Requires-Dist: odoo (<9.1a,>=9.0a)
